{
  "klass": "TrainerBattleSetup",
  "id": 60,
  "dbSymbol": "trainer_60",
  "vsType": 2,
  "isCouple": false,
  "baseMoney": 10,
  "ai": 3,
  "party": [
    {
      "specie": "makuhita",
      "form": 0,
      "shinySetup": {
        "kind": "automatic",
        "rate": -1
      },
      "levelSetup": {
        "kind": "fixed",
        "level": 16
      },
      "randomEncounterChance": 1,
      "expandPokemonSetup": [
        {
          "type": "evs",
          "value": {
            "hp": 0,
            "atk": 0,
            "dfe": 0,
            "spd": 0,
            "ats": 0,
            "dfs": 0
          }
        },
        {
          "type": "ivs",
          "value": {
            "hp": 15,
            "atk": 15,
            "dfe": 15,
            "spd": 15,
            "ats": 15,
            "dfs": 15
          }
        },
        {
          "type": "loyalty",
          "value": 70
        },
        {
          "type": "moves",
          "value": [
            "force_palm",
            "fake_out",
            "whirlwind",
            "__remove__"
          ]
        },
        {
          "type": "originalTrainerName",
          "value": "Luigi"
        },
        {
          "type": "originalTrainerId",
          "value": 0
        }
      ]
    },
    {
      "specie": "machop",
      "form": 0,
      "shinySetup": {
        "kind": "automatic",
        "rate": -1
      },
      "levelSetup": {
        "kind": "fixed",
        "level": 15
      },
      "randomEncounterChance": 1,
      "expandPokemonSetup": [
        {
          "type": "evs",
          "value": {
            "hp": 0,
            "atk": 0,
            "dfe": 0,
            "spd": 0,
            "ats": 0,
            "dfs": 0
          }
        },
        {
          "type": "ivs",
          "value": {
            "hp": 15,
            "atk": 15,
            "dfe": 15,
            "spd": 15,
            "ats": 15,
            "dfs": 15
          }
        },
        {
          "type": "loyalty",
          "value": 70
        },
        {
          "type": "moves",
          "value": [
            "seismic_toss",
            "low_kick",
            "low_sweep",
            "karate_chop"
          ]
        },
        {
          "type": "originalTrainerName",
          "value": "Luigi"
        },
        {
          "type": "originalTrainerId",
          "value": 0
        }
      ]
    }
  ],
  "bagEntries": [],
  "battleId": 0,
  "resources": {
    "artworkFull": "Crache-Feu_big",
    "artworkSmall": "Crache_feu_sma",
    "character": "",
    "musics": {
      "bgm": "",
      "defeat": "",
      "encounter": "",
      "victory": ""
    },
    "sprite": ""
  },
  "additionalDialogs": []
}